{"title":"Neurociência, neuroeducação, neurodidáctica e tecnologia","language":"portuguese","abstract":" ","keywords":"","authors":[{
	"name":"Claudia De Barros",
        "orcid":"0000-0002-2286-8674",
        "email":"claudia.barros@uam.es"
        },{
	"name":"Antonio Hernández Fernández",
        "orcid":"0000-0002-7807-4363",
        "email":"antonio.hernandez@ujaen.es"
        }],"publication_date":"2022-9-20","field":"Social Sciences","subfield":"Psychology","sub_subfield":"Developmental Psychology"}
